amsdal_data/Third-Party Materials - AMSDAL Dependencies - License Notices.md
amsdal_data/__about__.py
amsdal_data/__about__.pyi
amsdal_data/__init__.py
amsdal_data/__init__.pyi
amsdal_data/application.py
amsdal_data/application.pyi
amsdal_data/enums.py
amsdal_data/enums.pyi
amsdal_data/errors.py
amsdal_data/errors.pyi
amsdal_data/py.typed
amsdal_data/utils.py
amsdal_data/utils.pyi
amsdal_data/aliases/__init__.py
amsdal_data/aliases/__init__.pyi
amsdal_data/aliases/db.py
amsdal_data/aliases/db.pyi
amsdal_data/aliases/external.py
amsdal_data/aliases/external.pyi
amsdal_data/aliases/using.py
amsdal_data/aliases/using.pyi
amsdal_data/connections/__init__.py
amsdal_data/connections/__init__.pyi
amsdal_data/connections/async_sqlite_historical.py
amsdal_data/connections/async_sqlite_historical.pyi
amsdal_data/connections/base_sqlite_historical.py
amsdal_data/connections/base_sqlite_historical.pyi
amsdal_data/connections/common.py
amsdal_data/connections/common.pyi
amsdal_data/connections/constants.py
amsdal_data/connections/constants.pyi
amsdal_data/connections/db_alias_map.py
amsdal_data/connections/db_alias_map.pyi
amsdal_data/connections/postgresql_historical.py
amsdal_data/connections/postgresql_historical.pyi
amsdal_data/connections/postgresql_state.py
amsdal_data/connections/postgresql_state.pyi
amsdal_data/connections/sqlite_historical.py
amsdal_data/connections/sqlite_historical.pyi
amsdal_data/connections/external/__init__.py
amsdal_data/connections/external/__init__.pyi
amsdal_data/connections/external/base.py
amsdal_data/connections/external/base.pyi
amsdal_data/connections/external/email.py
amsdal_data/connections/external/email.pyi
amsdal_data/connections/external/imap.py
amsdal_data/connections/external/imap.pyi
amsdal_data/connections/external/read_only_postgres.py
amsdal_data/connections/external/read_only_postgres.pyi
amsdal_data/connections/external/read_only_sqlite.py
amsdal_data-0.5.27.dist-info/METADATA
amsdal_data-0.5.27.dist-info/WHEEL
amsdal_data-0.5.27.dist-info/top_level.txt
amsdal_data-0.5.27.dist-info/RECORD
amsdal_data-0.5.27.dist-info/licenses/LICENSE.txt
