Metadata-Version: 2.4
Name: amsdal_data
Version: 0.5.27
Summary: Data-layer for AMSDAL framework
Author-email: "A. Michael Salem" <ams@amsdal.com>
License: AMSDAL End User License Agreement
Project-URL: Documentation, https://pypi.org/project/amsdal_data/#readme
Project-URL: Issues, https://pypi.org/project/amsdal_data/#issues
Project-URL: Source, https://pypi.org/project/amsdal_data/
Classifier: Development Status :: 4 - Beta
Classifier: Programming Language :: Python
Classifier: Programming Language :: Python :: 3.11
Classifier: Programming Language :: Python :: 3.12
Classifier: Programming Language :: Python :: 3.13
Classifier: Programming Language :: Python :: Implementation :: CPython
Classifier: Programming Language :: Python :: Implementation :: PyPy
Requires-Python: <3.14,>=3.11
License-File: LICENSE.txt
Requires-Dist: pydantic~=2.12
Requires-Dist: pytz>=2024.1
Requires-Dist: amsdal_utils==0.5.*,>=0.5.3
Requires-Dist: amsdal-glue>=0.1.4
Requires-Dist: amsdal-glue-connections>=0.1.15
Requires-Dist: amsdal-glue-core>=0.1.7
Provides-Extra: postgres-c
Requires-Dist: amsdal-glue[postgres-c]; extra == "postgres-c"
Provides-Extra: postgres-binary
Requires-Dist: amsdal-glue[postgres-binary]; extra == "postgres-binary"
Provides-Extra: async-sqlite
Requires-Dist: amsdal-glue[async-sqlite]; extra == "async-sqlite"
Provides-Extra: celery
Requires-Dist: celery==5.4.*; extra == "celery"
Dynamic: license-file
